{
  "basics": {
    "name": "Reese Kisaba",
    "label": "Student",
    "picture": "https://rkisaba.github.io/images/Reese_Portrait.jpg",
    "email": "rkisaba@hawaii.edu",
    "phone": "808-294-5576",
    "website": "https://rkisaba.github.io",
    "summary": "I am studying for a B.B.A in Finance and Management Information Systems from the Shidler College of Business, but I am also working toward a Minor in Economics from the college of at the University of Hawaii. I expect to graduate in Spring, 2024.",
    "location": {
      "address": "",
      "postalCode": "96822",
      "city": "Honolulu",
      "countryCode": "USA",
      "region": "Hawaii"
    },
    "profiles": [
      {
        "network": "github",
        "username": "rkisaba",
        "url": "http://github.com/rkisaba"
      },
      {
        "network": "linkedin",
        "username": "reesekisaba",
        "url": "http://linkedin.com/in/reesekisaba"
      },
      {
        "network": "instagram",
        "username": "reesek2g",
        "url": "http://instagram.com/reesek2g"
      }
    ]
  },
  "interests": [
    {
      "name": "Video games",
      "keywords": [
        "Valorant",
        "Team Fight Tactics",
        "Destiny 2"
      ]
    },
    {
      "name": "Sports",
      "keywords": [
        "Baseball",
        "Football",
        "Basketball",
      ]
    },
    {
      "name": "All things fish",
      "keywords": [
        "Fishing",
        "Diving",
        "Fish Tanks",
      ]
    }
  ],
  "skills": [
    {
      "name": "Languages and Frameworks",
      "level": "",
      "keywords": [
        "C",
        "C++",
        "Java",
        "Javascript",
        "Assembly",
        "Common Lisp"
      ]
    },
    {
      "name": "Toolsets/OS",
      "level": "",
      "keywords": [
        "MacOS",
        "Ubuntu",
        "Git/GitHub",
        "g++",
        "TI LaunchPad"
      ]
    }
  ],
  "education": [
    {
      "institution": "University of Hawaii, Honolulu, HI",
      "area": "Finance, Management Information Systems, Economics (expected Spring 2024",
      "studyType": "B.B.A.",
      "startDate": "2020-08-23",
      "endDate": "Present",
      "gpa": "3.88",
      "courses": [
      ]
    }
  ],
  "work": [
    {
      "company": "UH Manoa Office of Admissions",
      "position": "Admissions Assistant",
      "website": "https://manoa.hawaii.edu/admissions/",
      "startDate": "2021-06-29",
      "endDate": "Present",
      "summary": "Student Admissions Assistant",
      "highlights": [
        "Assist students with application process and getting started immediately after acceptance"
      ]
    },
  "awards": [
    {
      "title": "Manoa Academic Merit Scholarship",
      "date": "2020-Present",
      "awarder": "University of Hawaii at Manoa",
      "summary": "Scholarship is awarded to incoming freshmen who displayed good academic standing throughout high school by having a GPA at or above 3.5, SAT score of at least 1200, or ACT score of at least 23 upon application"
    },
    {
      "title": "Dean's List",
      "date": "F20-Present",
      "awarder": "University of Hawaii",
      "summary": "Awarded to student's who show good academic standing while taking classes at UH Manoa"
    }
  ],
  "references": [
    {
      "name": "Available upon request",
      "reference": ""
    }
  ]
}
